intraCorr/__init__.py
intraCorr-0.0.3.dist-info/LICENSE
intraCorr-0.0.3.dist-info/METADATA
intraCorr-0.0.3.dist-info/WHEEL
intraCorr-0.0.3.dist-info/top_level.txt
intraCorr-0.0.3.dist-info/RECORD
