Metadata-Version: 2.1
Name: intraCorr
Version: 0.0.3
Summary: This package calculates the correlation within subjects for repeated observations
Home-page: https://github.com/JNandez/intraCorr
Author: Erika Munoz, Jose Nandez
Author-email: erika.munoz.datascientist@gmail.com, jose.nandez.ds@gmail.com
License: UNKNOWN
Platform: UNKNOWN
Classifier: Programming Language :: Python :: 3
Classifier: License :: OSI Approved :: GNU General Public License v3 (GPLv3)
Classifier: Operating System :: OS Independent
Requires-Dist: numpy (>=0.15)
Requires-Dist: pandas (>=0.23)
Requires-Dist: scipy (>=1.1)
Requires-Dist: matplotlib (>=3.0)
Requires-Dist: scikit-learn (>=0.19)
